{
	"views": [
		{
			"name":     "onload",
			"endpoint": "https://ameijer-app.ccvdev.nl/Examples/SendService/Endpoint.php",
			"elements": [
				{
					"name":         "description",
					"label":        "",
					"element_type": "text",
					"value":        "Bacon Ipsum"
				},
				{
					"name":         "insured_shipping",
					"label":        "Insured shipping",
					"element_type": "input_select",
					"options":      [
						{
							"label":    "No",
							"value":    "0",
							"selected": true
						},
						{
							"label": "Yes (+ &euro4,50)",
							"value": "1"
						}
					]
				},
				{
					"name":         "track_and_trace_prefix",
					"label":        "Track &amp; Trace prefix",
					"element_type": "input_text"
				},
				{
					"name":         "direct_download",
					"label":        "Download package label",
					"element_type": "input_checkbox",
					"value":        "1"
				},
				{
					"name":         "format_label",
					"label":        "Format label",
					"element_type": "input_radio",
					"options":      [
						{
							"label": "A4",
							"value": "A4"
						},
						{
							"label":    "A5",
							"value":    "A5",
							"selected": true
						},
						{
							"label": "A6",
							"value": "A6"
						}
					]
				},
				{
					"name":         "submit",
					"label":        "Submit",
					"value":        "send",
					"element_type": "input_button",
					"icon":         "fa-share"
				}
			]
		},
		{
			"name":     "succes",
			"endpoint": "https://ameijer-app.ccvdev.nl/Examples/SendService/Endpoint.php",
			"elements": [
				{
					"name":         "description",
					"label":        "Result",
					"element_type": "text"
				},
				{
					"name":         "package_label_1",
					"label":        "Package label",
					"element_type": "attachment",
					"icon":         "fa-file-pdf-o"
				}
			]
		},
		{
			"name":     "succes-direct-download",
			"endpoint": "https://ameijer-app.ccvdev.nl/Examples/SendService/Endpoint.php",
			"elements": [
				{
					"name":         "description",
					"label":        "Result",
					"element_type": "text"
				},
				{
					"name":         "package_label_1",
					"label":        "Package label",
					"element_type": "attachment",
					"icon":         "fa-file-pdf-o"
				},
				{
					"name":         "download_label_1",
					"label":        "",
					"element_type": "download"
				}
			]
		}
	]
}